onnxsim/__init__.py
onnxsim/__main__.py
onnxsim/cpp2py_export.cc
onnxsim/cxxopts.hpp
onnxsim/model_checking.py
onnxsim/model_info.py
onnxsim/onnx_simplifier.py
onnxsim/onnxsim.cpp
onnxsim/onnxsim.h
onnxsim/onnxsim_cpp2py_export.cpython-311-aarch64-linux-gnu.so
onnxsim/version.py
onnxsim/bin/onnxsim_bin.cpp
onnxsim/bin/onnxsim_option.cpp
onnxsim/bin/onnxsim_option.h
onnxsim_prebuilt-0.4.36.post1.dist-info/METADATA
onnxsim_prebuilt-0.4.36.post1.dist-info/WHEEL
onnxsim_prebuilt-0.4.36.post1.dist-info/entry_points.txt
onnxsim_prebuilt-0.4.36.post1.dist-info/top_level.txt
onnxsim_prebuilt-0.4.36.post1.dist-info/RECORD
onnxsim_prebuilt-0.4.36.post1.dist-info/licenses/LICENSE
